FindBadwords/__init__.py
FindBadwords/search.py
findbadwords-1.2.2.dist-info/METADATA
findbadwords-1.2.2.dist-info/WHEEL
findbadwords-1.2.2.dist-info/top_level.txt
findbadwords-1.2.2.dist-info/RECORD
