Metadata-Version: 2.4
Name: FindBadwords
Version: 1.2.2
Summary: Find any word in a sentence
Author: BOXER
Author-email: vagabonwalybi@gmail.com
Maintainer: BOXER
Maintainer-email: vagabonwalybi@gmail.com
Classifier: Programming Language :: Python :: 3.9
Classifier: License :: OSI Approved :: MIT License
Classifier: Natural Language :: English
Classifier: Operating System :: Microsoft :: Windows :: Windows 11
Classifier: Operating System :: Microsoft :: Windows :: Windows 10
Requires-Python: >=3.9
Requires-Dist: immutable-Python-Type
Requires-Dist: regex
Dynamic: author
Dynamic: author-email
Dynamic: classifier
Dynamic: description
Dynamic: maintainer
Dynamic: maintainer-email
Dynamic: requires-dist
Dynamic: requires-python
Dynamic: summary
